wagtail_localize_openai_translator-0.4.0.dist-info/METADATA
wagtail_localize_openai_translator-0.4.0.dist-info/WHEEL
wagtail_localize_openai_translator-0.4.0.dist-info/entry_points.txt
wagtail_localize_openai_translator-0.4.0.dist-info/licenses/LICENSE
wagtail_localize_openai_translator/__init__.py
wagtail_localize_openai_translator/translate.py
wagtail_localize_openai_translator-0.4.0.dist-info/RECORD
