Metadata-Version: 2.1
Name: wagtail-localize-openai-translator
Version: 0.4.0
Author-Email: Python Italia <help@pycon.it>
License: MIT
Requires-Python: >=3.11
Requires-Dist: openai>=1.51.2
